{"cameraMode":{"drawMode":0,"name":"Shaded","section":"Shading Mode"},"sceneLighting":true,"audioPlay":false,"sceneViewState":{"showFog":true,"showMaterialUpdate":false,"showSkybox":true,"showFlares":true,"showImageEffects":true,"showParticleSystems":true},"in2DMode":false,"pivot":{"x":0.16421201825141908,"y":10.40805721282959,"z":-2.3779237270355226},"rotation":{"x":-0.1375124454498291,"y":-0.7841745018959045,"z":0.5753645896911621,"w":-0.18742118775844575},"size":3.871577024459839,"orthographic":false}